{
    "National Geographic": {
        "image": "https://rigelapp.com/rigel-resources.github.io/sources/images/nationalGeographic.png",
        "weight": 8,
        "categories": [
            "History",
            "Science"
        ],
        "hasSubscription": false
    },
    "Nautilus": {
        "image": "https://rigelapp.com/rigel-resources.github.io/sources/images/nautilus.png",
        "weight": 9,
        "categories": [
            "Science"
        ],
        "hasSubscription": true
    },
    "Science Focus": {
        "image": "https://rigelapp.com/rigel-resources.github.io/sources/images/sciencefocus.png",
        "weight": 8,
        "categories": [
            "Science"
        ],
        "hasSubscription": false
    },
    "Weird Things": {
        "image": "https://rigelapp.com/rigel-resources.github.io/sources/images/weirdthings.png",
        "weight": 8,
        "categories": [
            "Science"
        ],
        "hasSubscription": false
    },
    "Sky and Telescope": {
        "image": "https://rigelapp.com/rigel-resources.github.io/sources/images/skyandtelescope.png",
        "weight": 8,
        "categories": [
            "Science"
        ],
        "hasSubscription": false
    },
    "History Today": {
        "image": "https://rigelapp.com/rigel-resources.github.io/sources/images/HT.png",
        "weight": 10,
        "categories": [
            "History"
        ],
        "hasSubscription": true
    },
    "Smithsonian Magazine": {
        "image": "https://rigelapp.com/rigel-resources.github.io/sources/images/smithsonian.png",
        "weight": 8,
        "categories": [
            "History",
            "Science",
            "Technology",
            "Food"
        ],
        "hasSubscription": false
    },
    "Archaeology": {
        "image": "https://rigelapp.com/rigel-resources.github.io/sources/images/archaeology.png",
        "weight": 7,
        "categories": [
            "History"
        ],
        "hasSubscription": false
    },
    "Entrepreneur": {
        "image": "https://rigelapp.com/rigel-resources.github.io/sources/images/entrepreneur.png",
        "weight": 8,
        "categories": [
            "Business"
        ],
        "hasSubscription": true
    },
    "Fast Company": {
        "image": "https://rigelapp.com/rigel-resources.github.io/sources/images/fastcompany.png",
        "weight": 9,
        "categories": [
            "Business"
        ],
        "hasSubscription": false
    },
    "Startups Magazine": {
        "image": "https://rigelapp.com/rigel-resources.github.io/sources/images/startupsmagazine.png",
        "weight": 9,
        "categories": [
            "Business"
        ],
        "hasSubscription": false
    },
    "Forbes": {
        "image": "https://rigelapp.com/rigel-resources.github.io/sources/images/forbes.png",
        "weight": 8,
        "categories": [
            "Business"
        ],
        "hasSubscription": false
    },
    "Innovators Mag": {
        "image": "https://rigelapp.com/rigel-resources.github.io/sources/images/innovatorsmag.png",
        "weight": 8,
        "categories": [
            "Technology"
        ],
        "hasSubscription": false
    },
    "MIT Technology Review": {
        "image": "https://rigelapp.com/rigel-resources.github.io/sources/images/MIT.png",
        "weight": 8,
        "categories": [
            "Technology"
        ],
        "hasSubscription": true
    },
    "Offscreen": {
        "image": "https://rigelapp.com/rigel-resources.github.io/sources/images/offscreen.png",
        "weight": 8,
        "categories": [
            "Technology"
        ],
        "hasSubscription": false
    },
    "Venture Beat": {
        "image": "https://rigelapp.com/rigel-resources.github.io/sources/images/venturebeat.png",
        "weight": 7,
        "categories": [
            "Technology"
        ],
        "hasSubscription": false
    },
    "Little White Lies": {
        "image": "https://rigelapp.com/rigel-resources.github.io/sources/images/lwl.png",
        "weight": 9,
        "categories": [
            "Cinema"
        ],
        "hasSubscription": false
    },
    "BBC": {
        "image": "https://rigelapp.com/rigel-resources.github.io/sources/images/BBC.png",
        "weight": 9,
        "categories": [
            "Cinema"
        ],
        "hasSubscription": false
    },
    "Empire": {
        "image": "https://rigelapp.com/rigel-resources.github.io/sources/images/empire.png",
        "weight": 8,
        "categories": [
            "Cinema"
        ],
        "hasSubscription": false
    },
    "Taste of Cinema": {
        "image": "",
        "weight": 8,
        "categories": [
            "Cinema"
        ],
        "hasSubscription": false
    },
    "Bon Appetit": {
        "image": "https://rigelapp.com/rigel-resources.github.io/sources/images/bonappetit.png",
        "weight": 8,
        "categories": [
            "Food"
        ],
        "hasSubscription": false
    },
    "Clean Eating": {
        "image": "https://rigelapp.com/rigel-resources.github.io/sources/images/cleaneating.png",
        "weight": 8,
        "categories": [
            "Food"
        ],
        "hasSubscription": false
    },
    "Eating Well": {
        "image": "https://rigelapp.com/rigel-resources.github.io/sources/images/eatingwell.png",
        "weight": 8,
        "categories": [
            "Food"
        ],
        "hasSubscription": false
    },
    "Healthy" : {
        "image": "https://rigelapp.com/rigel-resources.github.io/sources/images/healthy.png",
        "weight": 8,
        "categories": [
            "Food"
        ],
        "hasSubscription": false
    },
    "Smarthistory" : {
        "image": "https://yt3.ggpht.com/ytc/AAUvwnizm7vUSiRtDrtQ-_H3Mm0BRWXwVxzSucEmdtkOHQ",
        "weight": 10,
        "categories": [
            "Art"
        ],
        "hasSubscription": false
    },
    "Perspective" : {
        "image": "https://yt3.ggpht.com/ytc/AAUvwnhCg2m5gYKtZjJHIQ0ZVBP7yfRfKOZwDnLx3TwO",
        "weight": 7,
        "categories": [
            "Art"
        ],
        "hasSubscription": false
    },
    "Guggenheim Museum" : {
        "image": "https://yt3.ggpht.com/ytc/AAUvwnjLqmDJlAWR5aTas4133ua3PaKmPtc977kLYGxUKg",
        "weight": 8,
        "categories": [
            "Art"
        ],
        "hasSubscription": false
    },
    "The Met Museum" : {
        "image": "https://yt3.ggpht.com/ytc/AAUvwngNFbjGIda9VDeHshkrqGBiVa2oi9rKjXaomKfNSg",
        "weight": 8,
        "categories": [
            "Art"
        ],
        "hasSubscription": false
    },
    "The National Gallery" : {
        "image": "https://yt3.ggpht.com/ytc/AAUvwnhQtFdc11mEZ95_TFIDU3c5c8GDUuNDR91NiQ-HhU0",
        "weight": 8,
        "categories": [
            "Art"
        ],
        "hasSubscription": false
    },
    "The Museum of Modern Art" : {
        "image": "https://yt3.ggpht.com/ytc/AAUvwnhetxVn7wvGeOWAPjvGofGBuubNydDM2XcK4K_mfg",
        "weight": 8,
        "categories": [
            "Art"
        ],
        "hasSubscription": false
    },
    "Victoria and Albert Museum" : {
        "image": "https://rigelapp.com/rigel-resources.github.io/sources/images/vanda.jpg",
        "weight": 8,
        "categories": [
            "Art"
        ],
        "hasSubscription": false
    },
    "Museo Nacional del Prado" : {
        "image": "https://yt3.ggpht.com/ytc/AAUvwniD9CDfQG05FhOPkJjfng_kbZ5zi4xipL8ChSktSA",
        "weight": 8,
        "categories": [
            "Art"
        ],
        "hasSubscription": false
    },
    "Asian Art Museum" : {
        "image": "https://yt3.ggpht.com/ytc/AAUvwngNVrWtZLT-aLW5kh_EQr_k4VDLpQznAlM3MShW",
        "weight": 8,
        "categories": [
            "Art"
        ],
        "hasSubscription": false
    },
    "Art Institute of Chicago" : {
        "image": "https://yt3.ggpht.com/ytc/AAUvwng01wpMfvQZoO2dZ4ZsPa9FWqxtqp416VVO0HzDwg",
        "weight": 8,
        "categories": [
            "Art"
        ],
        "hasSubscription": false
    },
    "Biographics" : {
        "image": "https://yt3.ggpht.com/ytc/AAUvwni4vTHLr3aLt_AQayqxzXxs2uC7R4nwo9LNusKj",
        "weight": 8,
        "categories": [
            "History"
        ],
        "hasSubscription": false
    },
    "Science Magazine" : {
        "image": "https://yt3.ggpht.com/ytc/AAUvwniTiCLKdyuqv3J-V7gF09FeTmG0WGn7ZccOhNgVrA",
        "weight": 8,
        "categories": [
            "Science"
        ],
        "hasSubscription": false
    },
    "Scientific American" : {
        "image": "https://yt3.ggpht.com/ytc/AAUvwngcZ6rZxlCfuCkAIb_1aliOknI12MXW0DIf-JXIig",
        "weight": 8,
        "categories": [
            "Science"
        ],
        "hasSubscription": false
    }
}